[
  {
    "name": "Red Nike Air Max 270",
    "price": 2499,
    "rating": 4.5,
    "image_url": "https://via.placeholder.com/300x200/ff0000/ffffff?text=Nike+Air+Max",
    "description": "Comfortable running shoes with Air Max cushioning and breathable mesh upper",
    "buy_link": "https://www.google.com/search?q=Red+Nike+Air+Max+270+price+india",
    "category": "apparel",
    "brand": "Nike",
    "color": "red",
    "platform": "Google"
  },
  {
    "name": "Adidas Ultraboost 22 Red",
    "price": 2999,
    "rating": 4.3,
    "image_url": "https://via.placeholder.com/300x200/ff0000/ffffff?text=Adidas+Ultraboost",
    "description": "Premium running shoes with Boost technology and Continental rubber outsole",
    "buy_link": "https://www.google.com/search?q=Adidas+Ultraboost+22+Red+price+india",
    "category": "apparel",
    "brand": "Adidas",
    "color": "red",
    "platform": "Google"
  },
  {
    "name": "Puma RS-X Red",
    "price": 1899,
    "rating": 4.1,
    "image_url": "https://via.placeholder.com/300x200/ff0000/ffffff?text=Puma+RS-X",
    "description": "Retro-inspired sneakers with RS technology for superior comfort",
    "buy_link": "https://www.google.com/search?q=Puma+RS-X+Red+price+india",
    "category": "apparel",
    "brand": "Puma",
    "color": "red",
    "platform": "Google"
  },
  {
    "name": "Redmi Note 12 Pro",
    "price": 14999,
    "rating": 4.2,
    "image_url": "https://via.placeholder.com/300x200/0000ff/ffffff?text=Redmi+Note+12",
    "description": "6.67 inch AMOLED display, 108MP camera, 5000mAh battery, 67W fast charging",
    "buy_link": "https://www.google.com/search?q=Redmi+Note+12+Pro+price+india",
    "category": "mobiles",
    "brand": "Redmi",
    "color": "blue",
    "platform": "Google"
  },
  {
    "name": "Realme 10 Pro",
    "price": 13999,
    "rating": 4.1,
    "image_url": "https://via.placeholder.com/300x200/00ff00/ffffff?text=Realme+10+Pro",
    "description": "6.72 inch display, 108MP camera, 5000mAh battery, Snapdragon 695 processor",
    "buy_link": "https://www.google.com/search?q=Realme+10+Pro+price+india",
    "category": "mobiles",
    "brand": "Realme",
    "color": "black",
    "platform": "Google"
  },
  {
    "name": "Samsung Galaxy M34",
    "price": 15999,
    "rating": 4.3,
    "image_url": "https://via.placeholder.com/300x200/800080/ffffff?text=Samsung+M34",
    "description": "6.5 inch Super AMOLED, 50MP triple camera, 6000mAh battery, 5G ready",
    "buy_link": "https://www.google.com/search?q=Samsung+Galaxy+M34+price+india",
    "category": "mobiles",
    "brand": "Samsung",
    "color": "silver",
    "platform": "Google"
  },
  {
    "name": "HP Pavilion 15",
    "price": 45999,
    "rating": 4.3,
    "image_url": "https://via.placeholder.com/300x200/800080/ffffff?text=HP+Pavilion+15",
    "description": "Intel i5 12th Gen, 8GB RAM, 512GB SSD, 15.6 inch FHD display, Windows 11",
    "buy_link": "https://www.google.com/search?q=HP+Pavilion+15+laptop+price+india",
    "category": "electronics",
    "brand": "HP",
    "color": "silver",
    "platform": "Google"
  },
  {
    "name": "Dell Inspiron 15 3520",
    "price": 42999,
    "rating": 4.1,
    "image_url": "https://via.placeholder.com/300x200/008080/ffffff?text=Dell+Inspiron+15",
    "description": "AMD Ryzen 5 5500U, 8GB RAM, 512GB SSD, 15.6 inch FHD, Windows 11",
    "buy_link": "https://www.google.com/search?q=Dell+Inspiron+15+3520+price+india",
    "category": "electronics",
    "brand": "Dell",
    "color": "black",
    "platform": "Google"
  },
  {
    "name": "Lenovo IdeaPad Slim 3",
    "price": 39999,
    "rating": 4.0,
    "image_url": "https://via.placeholder.com/300x200/000000/ffffff?text=Lenovo+IdeaPad",
    "description": "Intel i3 12th Gen, 8GB RAM, 256GB SSD, 15.6 inch FHD, Windows 11",
    "buy_link": "https://www.google.com/search?q=Lenovo+IdeaPad+Slim+3+price+india",
    "category": "electronics",
    "brand": "Lenovo",
    "color": "platinum",
    "platform": "Google"
  },
  {
    "name": "ASUS VivoBook 15",
    "price": 37999,
    "rating": 4.2,
    "image_url": "https://via.placeholder.com/300x200/4CAF50/ffffff?text=ASUS+VivoBook",
    "description": "AMD Ryzen 3 5300U, 8GB RAM, 256GB SSD, 15.6 inch FHD, Windows 11",
    "buy_link": "https://www.google.com/search?q=ASUS+VivoBook+15+price+india",
    "category": "electronics",
    "brand": "ASUS",
    "color": "silver",
    "platform": "Google"
  },
  {
    "name": "Blue Denim Jacket",
    "price": 1299,
    "rating": 4.4,
    "image_url": "https://via.placeholder.com/300x200/0000ff/ffffff?text=Denim+Jacket",
    "description": "Classic denim jacket with button closure and chest pockets",
    "buy_link": "https://www.google.com/search?q=Blue+Denim+Jacket+Levi's+price+india",
    "category": "apparel",
    "brand": "Levi's",
    "color": "blue",
    "platform": "Google"
  },
  {
    "name": "Black Wireless Headphones",
    "price": 2999,
    "rating": 4.6,
    "image_url": "https://via.placeholder.com/300x200/000000/ffffff?text=Wireless+Headphones",
    "description": "Active noise cancellation, 30-hour battery life, Bluetooth 5.0",
    "buy_link": "https://www.google.com/search?q=Black+Wireless+Headphones+Sony+price+india",
    "category": "electronics",
    "brand": "Sony",
    "color": "black",
    "platform": "Google"
  }
]
